pypack/skeleton
