Metadata-Version: 1.2
Name: pypack.skeleton
Version: 1.0.2
Summary: This is test package for skeleton, DO NOT INSTALL IT
Home-page: https://github.com/pypack/pypack-skeleton
Author: Giovanni Cardamone
Author-email: g.cardamone2@gmail.com
License: MIT
Keywords: PyPack
Platform: UNKNOWN
Requires-Python: >=3
